circfirm_hello_world/__init__.py
circfirm_hello_world-0.0.4.dist-info/LICENSE
circfirm_hello_world-0.0.4.dist-info/METADATA
circfirm_hello_world-0.0.4.dist-info/WHEEL
circfirm_hello_world-0.0.4.dist-info/top_level.txt
circfirm_hello_world-0.0.4.dist-info/RECORD
